photoarchive/__init__.py
photoarchive/__main__.py
photoarchive/archive.py
photoarchive/filedata.py
photoarchive/persist.py
photoarchive/photocopy.py
photoarchive-0.5.dist-info/METADATA
photoarchive-0.5.dist-info/RECORD
photoarchive-0.5.dist-info/WHEEL
photoarchive-0.5.dist-info/top_level.txt
