Metadata-Version: 2.1
Name: photoarchive
Version: 0.5
Summary: A simple tool to archive photos
Home-page: https://github.com/roseeng/photoarchive
Author: Göran Roseen
Author-email: goran@roseen.se
License: MIT
Platform: UNKNOWN
Classifier: Programming Language :: Python :: 3
Classifier: License :: OSI Approved :: MIT License
Classifier: Operating System :: OS Independent
Requires-Dist: piexif
